vrchatosc/__init__.py
vrchatosc/vrchatosc.py
vrchatosc-1.1.0.dist-info/licenses/LICENSE
vrchatosc-1.1.0.dist-info/METADATA
vrchatosc-1.1.0.dist-info/WHEEL
vrchatosc-1.1.0.dist-info/top_level.txt
vrchatosc-1.1.0.dist-info/RECORD
