Metadata-Version: 2.4
Name: vrchatosc
Version: 1.1.0
Summary: A Python utility package for VRChat OSC communication.
Author-email: YT_Crafting <136029379+YTCrafting@users.noreply.github.com>
License: Apache-2.0
Project-URL: Homepage, https://github.com/YTCrafting/VRChatOSC
Classifier: Programming Language :: Python :: 3
Classifier: License :: OSI Approved :: Apache Software License
Classifier: Operating System :: OS Independent
Requires-Python: >=3.12
License-File: LICENSE
Requires-Dist: python-osc>=1.9.3
Dynamic: license-file
